new_trackr/__init__.py
new_trackr/api.py
new_trackr/device.py
new_trackr-0.0.3.dist-info/LICENSE
new_trackr-0.0.3.dist-info/METADATA
new_trackr-0.0.3.dist-info/WHEEL
new_trackr-0.0.3.dist-info/top_level.txt
new_trackr-0.0.3.dist-info/RECORD
