Metadata-Version: 2.1
Name: new-trackr
Version: 0.0.3
Summary: rewrite version of pytrackr.
Home-page: https://github.com/iessen/jcapi.git
Author: ewg
Author-email: essen.wang@outlook.com
License: UNKNOWN
Platform: UNKNOWN
Classifier: Programming Language :: Python :: 3
Classifier: License :: OSI Approved :: MIT License
Classifier: Operating System :: OS Independent
Requires-Python: >=3.6
